exprify/__init__.py
exprify/__main__.py
exprify/ast_transformer.py
exprify/injections.py
exprify/reflow.py
exprify/transpile.py
exprify-0.0.2.dist-info/licenses/LICENSE.txt
exprify-0.0.2.dist-info/METADATA
exprify-0.0.2.dist-info/WHEEL
exprify-0.0.2.dist-info/entry_points.txt
exprify-0.0.2.dist-info/top_level.txt
exprify-0.0.2.dist-info/RECORD
