Metadata-Version: 2.4
Name: exprify
Version: 0.0.2
Summary: Translates Python programs using statements into expressions
Author-email: Julius Park <juliusgeo@gmail.com>
Maintainer-email: Julius Park <juliusgeo@gmail.com>
License: The MIT License (MIT)
Keywords: expressions,transpiler,list comprehension
Classifier: Development Status :: 3 - Alpha
Classifier: Programming Language :: Python
Classifier: Programming Language :: Python :: 3
Classifier: Programming Language :: Python :: 3 :: Only
Classifier: Programming Language :: Python :: 3.11
Classifier: Programming Language :: Python :: 3.12
Classifier: Programming Language :: Python :: 3.13
Classifier: Programming Language :: Python :: 3.14
Requires-Python: >=3.11
License-File: LICENSE.txt
Requires-Dist: python-minifier
Dynamic: license-file
